euskalmet/__init__.py
euskalmet/__version__.py
euskalmet/euskalmet.py
euskalmet/exceptions.py
euskalmet/geo.py
euskalmet/stations.py
euskalmet/weather.py
python_euskalmet-0.3.4.dist-info/LICENSE
python_euskalmet-0.3.4.dist-info/METADATA
python_euskalmet-0.3.4.dist-info/WHEEL
python_euskalmet-0.3.4.dist-info/top_level.txt
python_euskalmet-0.3.4.dist-info/RECORD
