Metadata-Version: 2.1
Name: python-euskalmet
Version: 0.3.4
Summary: Python API for Euskalmet (https://www.euskalmet.euskadi.eus/hasiera/) open data
Home-page: https://github.com/r3v1/python-euskalmet
Author: David Revillas
Author-email: r3v1@pm.me
License: MIT
Project-URL: Bug Reports, https://gitlab.com/r3v1/python-euskalmet/issues
Keywords: euskalmet weather api euskadi "basque contry" opendata
Classifier: Development Status :: 1 - Planning
Classifier: Intended Audience :: Developers
Classifier: Topic :: Software Development :: Build Tools
Classifier: License :: OSI Approved :: MIT License
Classifier: Programming Language :: Python :: 3.8
Classifier: Programming Language :: Python :: 3.9
Classifier: Programming Language :: Python :: 3.10
Requires-Python: >=3.8
License-File: LICENSE
Requires-Dist: requests
Requires-Dist: tqdm
Requires-Dist: pandas
Requires-Dist: PyJWT (>=2.5.0)
Requires-Dist: pytz
Requires-Dist: cryptography
Requires-Dist: numpy
